django_langchain/__init__.py
django_langchain/admin.py
django_langchain/apps.py
django_langchain/models.py
django_langchain/tests.py
django_langchain/views.py
django_langchain/migrations/0001_initial.py
django_langchain/migrations/0002_alter_documentchunk_index.py
django_langchain/migrations/__init__.py
django_langchain-0.0.1.dist-info/LICENSE
django_langchain-0.0.1.dist-info/METADATA
django_langchain-0.0.1.dist-info/WHEEL
django_langchain-0.0.1.dist-info/top_level.txt
django_langchain-0.0.1.dist-info/RECORD
