Metadata-Version: 2.1
Name: django-langchain
Version: 0.0.1
Summary: Django Langchain
Home-page: https://github.com/paschembri/django-langchain
Author: P.A. SCHEMBRI
Author-email: pa.schembri@advanced-stack.com
License: All rights reserved. 2023
License-File: LICENSE
Requires-Dist: django
Requires-Dist: djangorestframework
Requires-Dist: langchain
Requires-Dist: sentence-transformers
Requires-Dist: unstructured
Requires-Dist: openai
Requires-Dist: pgvector
Requires-Dist: psycopg[binary]
